[
  {
    "key": "MC-FO",
    "name": "Fontvieille",
    "icon": false
  },
  {
    "key": "MC-JE",
    "name": "Jardin Exotique",
    "icon": false
  },
  {
    "key": "MC-CL",
    "name": "La Colle",
    "icon": false
  },
  {
    "key": "MC-CO",
    "name": "La Condamine",
    "icon": false
  },
  {
    "key": "MC-GA",
    "name": "La Gare",
    "icon": false
  },
  {
    "key": "MC-SO",
    "name": "La Source",
    "icon": false
  },
  {
    "key": "MC-LA",
    "name": "Larvotto",
    "icon": false
  },
  {
    "key": "MC-MA",
    "name": "Malbousquet",
    "icon": false
  },
  {
    "key": "MC-MO",
    "name": "Monaco-Ville",
    "icon": false
  },
  {
    "key": "MC-MG",
    "name": "Moneghetti",
    "icon": false
  },
  {
    "key": "MC-MC",
    "name": "Monte-Carlo",
    "icon": false
  },
  {
    "key": "MC-MU",
    "name": "Moulins",
    "icon": false
  },
  {
    "key": "MC-PH",
    "name": "Port-Hercule",
    "icon": false
  },
  {
    "key": "MC-SR",
    "name": "Saint-Roman",
    "icon": false
  },
  {
    "key": "MC-SD",
    "name": "Sainte-Dévote",
    "icon": false
  },
  {
    "key": "MC-SP",
    "name": "Spélugues",
    "icon": false
  },
  {
    "key": "MC-VR",
    "name": "Vallon de la Rousse",
    "icon": false
  }
]