[
  {
    "key": "SB-CT",
    "name": "Capital Territory",
    "icon": false
  },
  {
    "key": "SB-CE",
    "name": "Central",
    "icon": false
  },
  {
    "key": "SB-CH",
    "name": "Choiseul",
    "icon": false
  },
  {
    "key": "SB-GU",
    "name": "Guadalcanal",
    "icon": false
  },
  {
    "key": "SB-IS",
    "name": "Isabel",
    "icon": false
  },
  {
    "key": "SB-MK",
    "name": "Makira-Ulawa",
    "icon": false
  },
  {
    "key": "SB-ML",
    "name": "Malaita",
    "icon": false
  },
  {
    "key": "SB-RB",
    "name": "Rennell and Bellona",
    "icon": false
  },
  {
    "key": "SB-TE",
    "name": "Temotu",
    "icon": false
  },
  {
    "key": "SB-WE",
    "name": "Western",
    "icon": false
  }
]